{
    "parent": "block/block",
    "ambientocclusion": false,
    "elements": [
        {   "from": [ 0, 0, 0 ],
            "to": [ 16, 1, 16 ],
            "faces": {
                "down":  { "texture": "block", "cullface": "down" },
                "up":    { "texture": "block" },
                "north": { "uv": [ 0, 15, 16, 16 ], "texture": "#block", "cullface": "north" },
                "south": { "uv": [ 0, 15, 16, 16 ], "texture": "#block", "cullface": "south" },
                "west":  { "uv": [ 0, 15, 16, 16 ], "texture": "#block", "cullface": "west" },
                "east":  { "uv": [ 0, 15, 16, 16 ], "texture": "#block", "cullface": "east" }
            }
        },
        {   "from": [ 0, 1, 0 ],
            "to": [ 15, 16, 1 ],
            "faces": {
                "up":    { "uv": [ 0, 0, 15, 1 ], "texture": "#block", "cullface": "up" },
                "north": { "uv": [ 1, 0, 16, 15 ],  "texture": "#block", "cullface": "north" },
                "south": { "uv": [ 0, 0, 15, 15 ],  "texture": "#block" },
                "west":  { "uv": [ 0, 0, 1, 15], "texture": "#block", "cullface": "west" }
            }
        },
        {   "from": [ 15, 1, 0 ],
            "to": [ 16, 16, 15 ],
            "faces": {
                "up":    { "uv": [ 0, 0, 15, 1 ], "texture": "#block", "cullface": "up" },
                "east": { "uv": [ 1, 0, 16, 15 ],  "texture": "#block", "cullface": "east" },
                "west": { "uv": [ 0, 0, 15, 15 ],  "texture": "#block" },
                "north":  { "uv": [ 0, 0, 1, 15], "texture": "#block", "cullface": "north" }
            }
        },
        {   "from": [ 1, 1, 15 ],
            "to": [ 16, 16, 16 ],
            "faces": {
                "up":    { "uv": [ 0, 0, 15, 1 ], "texture": "#block", "cullface": "up" },
                "south": { "uv": [ 1, 0, 16, 15 ],  "texture": "#block", "cullface": "south" },
                "north": { "uv": [ 0, 0, 15, 15 ],  "texture": "#block" },
                "east":  { "uv": [ 0, 0, 1, 15], "texture": "#block", "cullface": "east" }
            }
        },
        {   "from": [ 0, 1, 1 ],
            "to": [ 1, 16, 16 ],
            "faces": {
                "up":    { "uv": [ 0, 0, 15, 1 ], "texture": "#block", "cullface": "up" },
                "west": { "uv": [ 1, 0, 16, 15 ],  "texture": "#block", "cullface": "west" },
                "east": { "uv": [ 0, 0, 15, 15 ],  "texture": "#block" },
                "south":  { "uv": [ 0, 0, 1, 15], "texture": "#block", "cullface": "south" }
            }
        }
    ],
    "textures": {
        "particle": "convenientadditions:blocks/composter/composter_block",
        "block": "convenientadditions:blocks/composter/composter_block"
    }
}
